{
  "anims": [
    {
      "key": "knight-idle",
      "frames": [
        { "key": "knight", "frame": 0 },
        { "key": "knight", "frame": 1 },
        { "key": "knight", "frame": 2 },
        { "key": "knight", "frame": 3 }
      ],
      "repeat": -1,
      "frameRate": 4
    },
    {
      "key": "knight-ready",
      "frames": [
        { "key": "knight", "frame": 4 },
        { "key": "knight", "frame": 5 },
        { "key": "knight", "frame": 6 },
        { "key": "knight", "frame": 7 }
      ],
      "repeat": -1,
      "frameRate": 4
    },
    {
      "key": "knight-run",
      "frames": [
        { "key": "knight", "frame": 8 },
        { "key": "knight", "frame": 9 },
        { "key": "knight", "frame": 10 },
        { "key": "knight", "frame": 11 },
        { "key": "knight", "frame": 12 },
        { "key": "knight", "frame": 13 },
        { "key": "knight", "frame": 14 },
        { "key": "knight", "frame": 15 }
      ],
      "repeat": -1,
      "frameRate": 8
    },
    {
      "key": "knight-attack",
      "frames": [
        { "key": "knight", "frame": 16 },
        { "key": "knight", "frame": 17 },
        { "key": "knight", "frame": 18 },
        { "key": "knight", "frame": 19 },
        { "key": "knight", "frame": 20 },
        { "key": "knight", "frame": 21 },
        { "key": "knight", "frame": 22 },
        { "key": "knight", "frame": 23 }
      ],
      "repeat": -1,
      "frameRate": 8
    }
  ]
}